clkhash/__init__.py
clkhash/benchmark.py
clkhash/bloomfilter.py
clkhash/clk.py
clkhash/comparators.py
clkhash/concurent_helpers.py
clkhash/data/ages.csv
clkhash/data/female-first-names.csv
clkhash/data/first-name-counts-by-year.csv
clkhash/data/last-names.csv
clkhash/data/male-first-names.csv
clkhash/data/randomnames-schema-v2.json
clkhash/data/randomnames-schema.json
clkhash/describe.py
clkhash/field_formats.py
clkhash/key_derivation.py
clkhash/randomnames.py
clkhash/schema.py
clkhash/schemas/v1.json
clkhash/schemas/v2.json
clkhash/schemas/v3.json
clkhash/serialization.py
clkhash/stats.py
clkhash/validate_data.py
clkhash-0.18.3.dist-info/LICENSE
clkhash-0.18.3.dist-info/METADATA
clkhash-0.18.3.dist-info/WHEEL
clkhash-0.18.3.dist-info/RECORD
