Metadata-Version: 2.1
Name: clkhash
Version: 0.18.3
Summary: Encoding utility to create Cryptographic Linkage Keys
Home-page: https://github.com/data61/clkhash
License: Apache
Author: Brian Thorne
Requires-Python: >=3.8,<4.0
Classifier: Development Status :: 5 - Production/Stable
Classifier: Environment :: Console
Classifier: License :: OSI Approved :: Apache Software License
Classifier: License :: Other/Proprietary License
Classifier: Natural Language :: English
Classifier: Operating System :: OS Independent
Classifier: Programming Language :: Python :: 3
Classifier: Programming Language :: Python :: 3.8
Classifier: Programming Language :: Python :: 3.9
Classifier: Programming Language :: Python :: 3.10
Classifier: Programming Language :: Python :: 3.11
Classifier: Programming Language :: Python :: Implementation :: CPython
Classifier: Programming Language :: Python :: Implementation :: PyPy
Classifier: Topic :: Security :: Cryptography
Requires-Dist: bitarray (>=2.6.0,<3.0.0)
Requires-Dist: cryptography (>=40.0,<41.0)
Requires-Dist: jsonschema (>=4.16.0,<5.0.0)
Requires-Dist: mypy_extensions (>=0.4.3,<0.5.0)
Requires-Dist: pyblake2 (>=1.1,<2.0) ; python_version < "3.6"
Requires-Dist: tqdm (>=4.65,<5.0)
Project-URL: Documentation, http://clkhash.readthedocs.io/
Project-URL: Repository, https://github.com/data61/clkhash
